milasdk/__init__.py
milasdk/api.py
milasdk/const.py
milasdk/exceptions.py
milasdk/auth/__init__.py
milasdk/auth/abstract_async_session.py
milasdk/auth/default_async_session.py
milasdk/auth/mila_oath2.py
milasdk/gql/__init__.py
milasdk/gql/enums.py
milasdk/gql/mila_schema.gql
milasdk/gql/queries.py
milasdk/gql/scalars.py
milasdk/gql/transport.py
milasdk/gql/types.py
milasdklite-0.0.2.dist-info/LICENSE
milasdklite-0.0.2.dist-info/METADATA
milasdklite-0.0.2.dist-info/WHEEL
milasdklite-0.0.2.dist-info/top_level.txt
milasdklite-0.0.2.dist-info/RECORD
