Metadata-Version: 2.1
Name: milasdklite
Version: 0.0.2
Summary: Python SDK for Mila Air Purifiers
Home-page: https://github.com/tombrien/milasdklite
Author: Tom brien
Author-email: tom@tombrien.io
License: MIT
Classifier: License :: OSI Approved :: MIT License
Classifier: Programming Language :: Python :: 3
Classifier: Programming Language :: Python :: 3.9
License-File: LICENSE
Requires-Dist: aiohttp
Requires-Dist: magicattr
Requires-Dist: gql
Requires-Dist: StrEnum
Requires-Dist: oauthlib
Requires-Dist: async-oauthlib
